aind_slims_api/__init__.py
aind_slims_api/configuration.py
aind_slims_api/core.py
aind_slims_api/exceptions.py
aind_slims_api/filters.py
aind_slims_api/types.py
aind_slims_api/models/__init__.py
aind_slims_api/models/attachment.py
aind_slims_api/models/base.py
aind_slims_api/models/behavior_session.py
aind_slims_api/models/ecephys_session.py
aind_slims_api/models/experiment_run_step.py
aind_slims_api/models/histology.py
aind_slims_api/models/imaging.py
aind_slims_api/models/instrument.py
aind_slims_api/models/metadata.py
aind_slims_api/models/mouse.py
aind_slims_api/models/unit.py
aind_slims_api/models/user.py
aind_slims_api/models/utils.py
aind_slims_api/models/waterlog_result.py
aind_slims_api/models/waterlog_water_restriction.py
aind_slims_api/operations/__init__.py
aind_slims_api/operations/ecephys_session.py
aind_slims_api/operations/histology_procedures.py
aind_slims_api/operations/spim_imaging.py
aind_slims_api-0.1.23.dist-info/licenses/LICENSE
aind_slims_api-0.1.23.dist-info/METADATA
aind_slims_api-0.1.23.dist-info/WHEEL
aind_slims_api-0.1.23.dist-info/top_level.txt
aind_slims_api-0.1.23.dist-info/RECORD
